README.md
setup.py
o2_scrap/__init__.py
o2_scrap/o2_scrap.py
o2_scrap/version.py
o2_scrap.egg-info/PKG-INFO
o2_scrap.egg-info/SOURCES.txt
o2_scrap.egg-info/dependency_links.txt
o2_scrap.egg-info/not-zip-safe
o2_scrap.egg-info/requires.txt
o2_scrap.egg-info/top_level.txt