Metadata-Version: 1.1
Name: o2-scrap
Version: 0.8
Summary: library to get data-usage and plan details from O2 germany mobile contracts
Home-page: http://github.com/grindsa/o2_scrap
Author: grindsa
Author-email: grindelsack@gmail.com
License: GPL
Platform: UNKNOWN
Classifier: Programming Language :: Python
Classifier: Development Status :: 4 - Beta
Classifier: Natural Language :: German
Classifier: Intended Audience :: Developers
Classifier: License :: OSI Approved :: GNU General Public License v3 or later (GPLv3+)
Classifier: Operating System :: OS Independent
Classifier: Topic :: Software Development :: Libraries :: Python Modules
